tiny8/__init__.py
tiny8/assembler.py
tiny8/cpu.py
tiny8/memory.py
tiny8/parser.py
tiny8/py.typed
tiny8/visualizer.py
tiny8-0.1.0.dist-info/WHEEL
tiny8-0.1.0.dist-info/METADATA
tiny8-0.1.0.dist-info/RECORD
