Metadata-Version: 2.3
Name: tiny8
Version: 0.1.0
Summary: Simulator for an 8-bit CPU with registers, memory, and a stack.
Author: sql-hkr
Author-email: sql-hkr <sql.hkr@gmail.com>
Classifier: License :: OSI Approved :: MIT License
Classifier: Programming Language :: Python :: 3.11
Classifier: Programming Language :: Python :: 3.12
Classifier: Programming Language :: Python :: 3.13
Requires-Dist: matplotlib>=3.10.7
Requires-Python: >=3.11
